KyreneCovidChecker/__init__.py
KyreneCovidChecker/__main__.py
KyreneCovidChecker/main.py
KyreneCovidChecker-0.0.1.dist-info/LICENSE
KyreneCovidChecker-0.0.1.dist-info/METADATA
KyreneCovidChecker-0.0.1.dist-info/WHEEL
KyreneCovidChecker-0.0.1.dist-info/entry_points.txt
KyreneCovidChecker-0.0.1.dist-info/top_level.txt
KyreneCovidChecker-0.0.1.dist-info/RECORD
