Metadata-Version: 2.1
Name: KyreneCovidChecker
Version: 0.0.1
Summary: Scrape the Kyrene COVID Dashboard
Home-page: https://github.com/trekie86/KyreneCovidChecker
Author: Rob Wolinski
Author-email: trekie86@gmail.com
License: MIT
Platform: UNKNOWN
Requires-Python: >=3.9
License-File: LICENSE
Requires-Dist: beautifulsoup4
Requires-Dist: alive-progress
